bosonic_qiskit-14.0.dist-info/licenses/LICENSE
c2qa/__init__.py
c2qa/animate.py
c2qa/circuit.py
c2qa/discretize.py
c2qa/kraus.py
c2qa/operators.py
c2qa/parameterized_unitary_gate.py
c2qa/qumoderegister.py
c2qa/util.py
c2qa/wigner.py
bosonic_qiskit-14.0.dist-info/METADATA
bosonic_qiskit-14.0.dist-info/WHEEL
bosonic_qiskit-14.0.dist-info/top_level.txt
bosonic_qiskit-14.0.dist-info/RECORD
