Metadata-Version: 2.4
Name: bosonic-qiskit
Version: 14.0
Summary: National Quantum Initiative Co-design Center for Quantum Advantage bosonic Qiskit simulator
Author-email: Tim Stavenger <timothy.stavenger@pnnl.gov>
License: Copyright 2022 Battelle Memorial Institute
Project-URL: Homepage, https://github.com/C2QA/bosonic-qiskit
Project-URL: Issues, https://github.com/C2QA/bosonic-qiskit/issues
Classifier: Programming Language :: Python :: 3
Classifier: Programming Language :: Python :: 3.9
Classifier: Programming Language :: Python :: 3.10
Classifier: Programming Language :: Python :: 3.11
Classifier: Programming Language :: Python :: 3.12
Classifier: Programming Language :: Python :: 3.13
Classifier: Operating System :: OS Independent
Requires-Python: >=3.9
License-File: LICENSE
Requires-Dist: qiskit==2.0.0
Requires-Dist: qiskit-aer==0.17.0
Requires-Dist: qiskit-ibm-runtime==0.38.0
Requires-Dist: qutip>=5.0.4
Requires-Dist: numpy>=2.0.2
Requires-Dist: scipy>=1.13.1
Requires-Dist: matplotlib>=3.9.4
Requires-Dist: pylatexenc==2.10
Dynamic: license-file
